saaps/__init__.py
saaps/constant.py
saaps/functions.py
saaps/main.py
saaps/test/Concise_Result.txt
saaps/test/Detail_Result.txt
saaps/test/IC-Plot.pdf
saaps/test/IC-Plot.png
saaps/test/NewNameSeq.txt
saaps/test/OneHot-ConciseMatrix.csv
saaps/test/OneHot-ForIntersect.csv
saaps/test/OneHot-Original.csv
saaps/test/OneHot-Transform.csv
saaps/test/PCA-Plot.pdf
saaps/test/PCA-Plot.png
saaps/test/PCA.csv
saaps/test/SAPs.pdf
saaps/test/SAPs.png
saaps/test/Seq_Matrix.csv
saaps/test/Shannon_IC_Result.csv
saaps/test/Shannon_log.txt
saaps/test/namesSeqName.csv
saaps/test/testSeq.txt
saaps-1.4.1.dist-info/LICENSE
saaps-1.4.1.dist-info/METADATA
saaps-1.4.1.dist-info/WHEEL
saaps-1.4.1.dist-info/entry_points.txt
saaps-1.4.1.dist-info/top_level.txt
saaps-1.4.1.dist-info/RECORD
